{
    "name": "horseshit",
    "date": "2013-01-14",
    
    "author": "Mort Yao",
    "author_email": "mort.yao@gmail.com",
    "url": "http://www.soimort.org/horseshit/",
    "license": "MIT",
    
    "description": "Small script to configure your hosts file so you don't get distracted during the day",
    "keywords": "hosts",
    
    "classifiers": [
        "Development Status :: 3 - Alpha",
        "Environment :: Console",
        "Intended Audience :: Developers",
        "Intended Audience :: Science/Research",
        "License :: OSI Approved :: MIT License",
        "Natural Language :: English",
        "Operating System :: OS Independent",
        "Programming Language :: Python",
        "Programming Language :: Python :: 2",
        "Programming Language :: Python :: 2.3",
        "Programming Language :: Python :: 2.4",
        "Programming Language :: Python :: 2.5",
        "Programming Language :: Python :: 2.6",
        "Programming Language :: Python :: 2.7",
        "Programming Language :: Python :: 3",
        "Programming Language :: Python :: 3.0",
        "Programming Language :: Python :: 3.1",
        "Programming Language :: Python :: 3.2",
        "Programming Language :: Python :: 3.3",
        "Topic :: Office/Business :: Scheduling"
    ],
    
    "console_scripts": [
        "get-shit-done = horseshit.main:main"
    ]
}
